synd/__init__.py
synd/cli.py
synd/core.py
synd/hosted.py
synd/synd.py
synd/models/__init__.py
synd/models/base.py
synd/models/discrete/__init__.py
synd/models/discrete/discrete.py
synd/models/discrete/markov.py
synd/westpa/__init__.py
synd/westpa/augmentation_driver.py
synd/westpa/propagator.py
SynD-0.1.4.dist-info/METADATA
SynD-0.1.4.dist-info/WHEEL
SynD-0.1.4.dist-info/top_level.txt
SynD-0.1.4.dist-info/RECORD
